mon_package_0178/__init__.py
mon_package_0178/mon_module_0178.py
mon_package_0178-0.1.dist-info/METADATA
mon_package_0178-0.1.dist-info/WHEEL
mon_package_0178-0.1.dist-info/top_level.txt
mon_package_0178-0.1.dist-info/RECORD
