Metadata-Version: 2.1
Name: mon-package-0178
Version: 0.1
Summary: Un exemple de package Python
Home-page: https://github.com/votrecompte/mon_package
Author: Martin SANTORO
Author-email: ms.martin.santoro@gmail.com
License: UNKNOWN
Platform: UNKNOWN
